corenlp_xml_reader
