Metadata-Version: 1.1
Name: corenlp-xml-reader
Version: 0.1.1
Summary: Work with CoreNLP annotations in Python
Home-page: https://github.com/enewe101/corenlp-xml-reader
Author: Edward Newell
Author-email: edward.newell@gmail.com
License: MIT
Keywords: NLP natrual language processing computational linguistics CoreNLP Stanford parser
Platform: UNKNOWN
Classifier: Development Status :: 3 - Alpha
Classifier: Intended Audience :: Developers
Classifier: Topic :: Software Development :: Build Tools
Classifier: License :: OSI Approved :: MIT License
Classifier: Programming Language :: Python :: 2.7
